ai_model_scanner/__init__.py
ai_model_scanner/cache.py
ai_model_scanner/cli.py
ai_model_scanner/config.py
ai_model_scanner/duplicate_detector.py
ai_model_scanner/formatters.py
ai_model_scanner/model_analyzer.py
ai_model_scanner/path_detector.py
ai_model_scanner/reference_finder.py
ai_model_scanner/scanner.py
ai_model_scanner/tool_detector.py
ai_model_scanner/utils.py
ai_model_scanner/watcher.py
ai_model_scanner-0.1.0.dist-info/licenses/LICENSE
ai_model_scanner-0.1.0.dist-info/METADATA
ai_model_scanner-0.1.0.dist-info/WHEEL
ai_model_scanner-0.1.0.dist-info/entry_points.txt
ai_model_scanner-0.1.0.dist-info/top_level.txt
ai_model_scanner-0.1.0.dist-info/RECORD
