Metadata-Version: 2.4
Name: ai-model-scanner
Version: 0.1.0
Summary: Lightweight cross-platform tool to scan for local AI model files
Author: AI Model Scanner Contributors
License: MIT
Project-URL: Homepage, https://github.com/MichaelWeed/ai-model-scanner
Project-URL: Documentation, https://github.com/MichaelWeed/ai-model-scanner#readme
Project-URL: Repository, https://github.com/MichaelWeed/ai-model-scanner
Project-URL: Issues, https://github.com/MichaelWeed/ai-model-scanner/issues
Keywords: ai,models,scanner,llm,machine-learning,ollama,huggingface
Classifier: Development Status :: 4 - Beta
Classifier: Intended Audience :: Developers
Classifier: License :: OSI Approved :: MIT License
Classifier: Programming Language :: Python :: 3
Classifier: Programming Language :: Python :: 3.9
Classifier: Programming Language :: Python :: 3.10
Classifier: Programming Language :: Python :: 3.11
Classifier: Programming Language :: Python :: 3.12
Classifier: Operating System :: OS Independent
Classifier: Topic :: Utilities
Classifier: Topic :: System :: Filesystems
Requires-Python: >=3.9
License-File: LICENSE
Requires-Dist: typer[all]>=0.9.0
Requires-Dist: rich>=13.0.0
Requires-Dist: watchdog>=3.0.0
Requires-Dist: toml>=0.10.2
Requires-Dist: plyer>=2.1.0
Provides-Extra: dev
Requires-Dist: pytest>=7.0.0; extra == "dev"
Requires-Dist: pytest-cov>=4.0.0; extra == "dev"
Requires-Dist: ruff>=0.1.0; extra == "dev"
Requires-Dist: build>=0.10.0; extra == "dev"
Requires-Dist: twine>=4.0.0; extra == "dev"
Dynamic: license-file
